A51/A5_1.v
module A5_1 (
    input clk, 
    input reset, 
    input [63:0] key, 
    input [63:0] plaintext,  // 新增的明文输入
    output wire z, 
    output reg [63:0] ciphertext  // 新增的密文输出
);

    reg [18:0] R1;
    reg [21:0] R2;
    reg [22:0] R3;
    
    assign z = R1[18] ^ R2[21] ^ R3[22];
    
always @(posedge clk or posedge reset) begin
    if (reset) begin
        R1 <= key[18:0];
        R2 <= key[39:19];
        R3 <= key[63:40];
        ciphertext <= 64'h0;  // 在复位时清空密文
    end else begin
        if ((R1[8] ^ R2[10] ^ R3[10]) == 1'b1) begin
            R1 <= {R1[13] ^ R1[16] ^ R1[17] ^ R1[18], R1[17:0]};
        end
        if ((R2[10] ^ R1[8] ^ R3[10]) == 1'b1) begin
            R2 <= {R2[20] ^ R2[21], R2[20:0]};
        end
        if ((R3[10] ^ R1[8] ^ R2[10]) == 1'b1) begin
            R3 <= {R3[7] ^ R3[20] ^ R3[21] ^ R3[22], R3[21:0]};
        end
        ciphertext <= plaintext ^ {64{z}};  // 更新密文
    end
end
endmodule

A51/A5_1_test.v
`timescale 1ns / 1ps

module A5_1_test;
    reg clk;
    reg reset;
    reg [63:0] key;
    reg [63:0] plaintext;  // 新增明文输入
    wire z;
    wire [63:0] ciphertext;  // 新增密文输出

    // 实例化A5/1模块
    A5_1 u1 (.clk(clk), .reset(reset), .key(key), .plaintext(plaintext), .z(z), .ciphertext(ciphertext));

    initial begin
        // 初始化输入信号
        clk = 0;
        reset = 0;
        key = 64'h123456789ABCDEF0;
        plaintext = 64'hFEDCBA9876543210;  // 初始化明文
       
        // 指定VCD文件的名称并打开它
        $dumpfile("A5_1_test.vcd");
        $dumpvars(0, A5_1_test);
        
        // 重置A5/1模块
        reset = 1;
        #10 reset = 0;
        
        // 生成时钟信号并观察输出
        repeat (100) begin
            #10 clk = ~clk;
            plaintext = {plaintext[62:0], plaintext[63]};  // 将明文左移一位
            $display("At time %t, z = %b, ciphertext = %h", $time, z, ciphertext);
        end
        
        // 结束仿真
        $finish;
    end
    
    always #5 clk = ~clk;
endmodule

A51/A5_1_test.vcd
$date
	Fri Dec 01 18:43:27 2023
$end
$version
	Icarus Verilog
$end
$timescale
	1ps
$end
$scope module A5_1_test $end
$var wire 1 ! z $end
$var wire 64 " ciphertext [63:0] $end
$var reg 1 # clk $end
$var reg 64 $ key [63:0] $end
$var reg 64 % plaintext [63:0] $end
$var reg 1 & reset $end
$scope module u1 $end
$var wire 1 # clk $end
$var wire 64 ' key [63:0] $end
$var wire 64 ( plaintext [63:0] $end
$var wire 1 & reset $end
$var wire 1 ! z $end
$var reg 19 ) R1 [18:0] $end
$var reg 22 * R2 [21:0] $end
$var reg 23 + R3 [22:0] $end
$var reg 64 , ciphertext [63:0] $end
$upscope $end
$upscope $end
$enddefinitions $end
#0
$dumpvars
b0 ,
b100100011010001010110 +
b11110001001101010111 *
b1001101111011110000 )
b1111111011011100101110101001100001110110010101000011001000010000 (
b1001000110100010101100111100010011010101111001101111011110000 '
1&
b1111111011011100101110101001100001110110010101000011001000010000 %
b1001000110100010101100111100010011010101111001101111011110000 $
0#
b0 "
1!
$end
#5000
1#
#10000
0#
0&
#15000
0!
b100100011010001010110011110001001101010111100110111101111 "
b100100011010001010110011110001001101010111100110111101111 ,
b10100100011010001010110 +
1#
#20000
1!
b1111110110111001011101010011000011101100101010000110010000100001 "
b1111110110111001011101010011000011101100101010000110010000100001 ,
b100100011010001010110 +
b1111110110111001011101010011000011101100101010000110010000100001 %
b1111110110111001011101010011000011101100101010000110010000100001 (
1#
#25000
0#
#30000
0!
b10010001101000101011001111000100110101011110011011110111100 "
b10010001101000101011001111000100110101011110011011110111100 ,
b10100100011010001010110 +
b1111101101110010111010100110000111011001010100001100100001000011 %
b1111101101110010111010100110000111011001010100001100100001000011 (
0#
#35000
1!
b1111101101110010111010100110000111011001010100001100100001000011 "
b1111101101110010111010100110000111011001010100001100100001000011 ,
b100100011010001010110 +
1#
#40000
0!
b100100011010001010110011110001001101010111100110111101111000 "
b100100011010001010110011110001001101010111100110111101111000 ,
b10100100011010001010110 +
b1111011011100101110101001100001110110010101000011001000010000111 %
b1111011011100101110101001100001110110010101000011001000010000111 (
1#
#45000
0#
#50000
1!
b1110110111001011101010011000011101100101010000110010000100001111 "
b1110110111001011101010011000011101100101010000110010000100001111 ,
b100100011010001010110 +
b1110110111001011101010011000011101100101010000110010000100001111 %
b1110110111001011101010011000011101100101010000110010000100001111 (
0#
#55000
0!
b1001000110100010101100111100010011010101111001101111011110000 "
b1001000110100010101100111100010011010101111001101111011110000 ,
b10100100011010001010110 +
1#
#60000
1!
b1101101110010111010100110000111011001010100001100100001000011111 "
b1101101110010111010100110000111011001010100001100100001000011111 ,
b100100011010001010110 +
b1101101110010111010100110000111011001010100001100100001000011111 %
b1101101110010111010100110000111011001010100001100100001000011111 (
1#
#65000
0#
#70000
0!
b100100011010001010110011110001001101010111100110111101111000000 "
b100100011010001010110011110001001101010111100110111101111000000 ,
b10100100011010001010110 +
b1011011100101110101001100001110110010101000011001000010000111111 %
b1011011100101110101001100001110110010101000011001000010000111111 (
0#
#75000
1!
b1011011100101110101001100001110110010101000011001000010000111111 "
b1011011100101110101001100001110110010101000011001000010000111111 ,
b100100011010001010110 +
1#
#80000
0!
b1001000110100010101100111100010011010101111001101111011110000000 "
b1001000110100010101100111100010011010101111001101111011110000000 ,
b10100100011010001010110 +
b110111001011101010011000011101100101010000110010000100001111111 %
b110111001011101010011000011101100101010000110010000100001111111 (
1#
#85000
0#
#90000
1!
b1101110010111010100110000111011001010100001100100001000011111110 "
b1101110010111010100110000111011001010100001100100001000011111110 ,
b100100011010001010110 +
b1101110010111010100110000111011001010100001100100001000011111110 %
b1101110010111010100110000111011001010100001100100001000011111110 (
0#
#95000
0!
b10001101000101011001111000100110101011110011011110111100000001 "
b10001101000101011001111000100110101011110011011110111100000001 ,
b10100100011010001010110 +
1#
#100000
1!
b1011100101110101001100001110110010101000011001000010000111111101 "
b1011100101110101001100001110110010101000011001000010000111111101 ,
b100100011010001010110 +
b1011100101110101001100001110110010101000011001000010000111111101 %
b1011100101110101001100001110110010101000011001000010000111111101 (
1#
#105000
0#
#110000
0!
b1000110100010101100111100010011010101111001101111011110000000100 "
b1000110100010101100111100010011010101111001101111011110000000100 ,
b10100100011010001010110 +
b111001011101010011000011101100101010000110010000100001111111011 %
b111001011101010011000011101100101010000110010000100001111111011 (
0#
#115000
1!
b111001011101010011000011101100101010000110010000100001111111011 "
b111001011101010011000011101100101010000110010000100001111111011 ,
b100100011010001010110 +
1#
#120000
0!
b1101000101011001111000100110101011110011011110111100000001001 "
b1101000101011001111000100110101011110011011110111100000001001 ,
b10100100011010001010110 +
b1110010111010100110000111011001010100001100100001000011111110110 %
b1110010111010100110000111011001010100001100100001000011111110110 (
1#
#125000
0#
#130000
1!
b1100101110101001100001110110010101000011001000010000111111101101 "
b1100101110101001100001110110010101000011001000010000111111101101 ,
b100100011010001010110 +
b1100101110101001100001110110010101000011001000010000111111101101 %
b1100101110101001100001110110010101000011001000010000111111101101 (
0#
#135000
0!
b11010001010110011110001001101010111100110111101111000000010010 "
b11010001010110011110001001101010111100110111101111000000010010 ,
b10100100011010001010110 +
1#
#140000
1!
b1001011101010011000011101100101010000110010000100001111111011011 "
b1001011101010011000011101100101010000110010000100001111111011011 ,
b100100011010001010110 +
b1001011101010011000011101100101010000110010000100001111111011011 %
b1001011101010011000011101100101010000110010000100001111111011011 (
1#
#145000
0#
#150000
0!
b1101000101011001111000100110101011110011011110111100000001001000 "
b1101000101011001111000100110101011110011011110111100000001001000 ,
b10100100011010001010110 +
b10111010100110000111011001010100001100100001000011111110110111 %
b10111010100110000111011001010100001100100001000011111110110111 (
0#
#155000
1!
b10111010100110000111011001010100001100100001000011111110110111 "
b10111010100110000111011001010100001100100001000011111110110111 ,
b100100011010001010110 +
1#
#160000
0!
b1010001010110011110001001101010111100110111101111000000010010001 "
b1010001010110011110001001101010111100110111101111000000010010001 ,
b10100100011010001010110 +
b101110101001100001110110010101000011001000010000111111101101110 %
b101110101001100001110110010101000011001000010000111111101101110 (
1#
#165000
0#
#170000
1!
b1011101010011000011101100101010000110010000100001111111011011100 "
b1011101010011000011101100101010000110010000100001111111011011100 ,
b100100011010001010110 +
b1011101010011000011101100101010000110010000100001111111011011100 %
b1011101010011000011101100101010000110010000100001111111011011100 (
0#
#175000
0!
b100010101100111100010011010101111001101111011110000000100100011 "
b100010101100111100010011010101111001101111011110000000100100011 ,
b10100100011010001010110 +
1#
#180000
1!
b111010100110000111011001010100001100100001000011111110110111001 "
b111010100110000111011001010100001100100001000011111110110111001 ,
b100100011010001010110 +
b111010100110000111011001010100001100100001000011111110110111001 %
b111010100110000111011001010100001100100001000011111110110111001 (
1#
#185000
0#
#190000
0!
b1010110011110001001101010111100110111101111000000010010001101 "
b1010110011110001001101010111100110111101111000000010010001101 ,
b10100100011010001010110 +
b1110101001100001110110010101000011001000010000111111101101110010 %
b1110101001100001110110010101000011001000010000111111101101110010 (
0#
#195000
1!
b1110101001100001110110010101000011001000010000111111101101110010 "
b1110101001100001110110010101000011001000010000111111101101110010 ,
b100100011010001010110 +
1#
#200000
0!
b10101100111100010011010101111001101111011110000000100100011010 "
b10101100111100010011010101111001101111011110000000100100011010 ,
b10100100011010001010110 +
b1101010011000011101100101010000110010000100001111111011011100101 %
b1101010011000011101100101010000110010000100001111111011011100101 (
1#
#205000
0#
#210000
1!
b1010100110000111011001010100001100100001000011111110110111001011 "
b1010100110000111011001010100001100100001000011111110110111001011 ,
b100100011010001010110 +
b1010100110000111011001010100001100100001000011111110110111001011 %
b1010100110000111011001010100001100100001000011111110110111001011 (
0#
#215000
0!
b101011001111000100110101011110011011110111100000001001000110100 "
b101011001111000100110101011110011011110111100000001001000110100 ,
b10100100011010001010110 +
1#
#220000
1!
b101001100001110110010101000011001000010000111111101101110010111 "
b101001100001110110010101000011001000010000111111101101110010111 ,
b100100011010001010110 +
b101001100001110110010101000011001000010000111111101101110010111 %
b101001100001110110010101000011001000010000111111101101110010111 (
1#
#225000
0#
#230000
0!
b101100111100010011010101111001101111011110000000100100011010001 "
b101100111100010011010101111001101111011110000000100100011010001 ,
b10100100011010001010110 +
b1010011000011101100101010000110010000100001111111011011100101110 %
b1010011000011101100101010000110010000100001111111011011100101110 (
0#
#235000
1!
b1010011000011101100101010000110010000100001111111011011100101110 "
b1010011000011101100101010000110010000100001111111011011100101110 ,
b100100011010001010110 +
1#
#240000
0!
b1011001111000100110101011110011011110111100000001001000110100010 "
b1011001111000100110101011110011011110111100000001001000110100010 ,
b10100100011010001010110 +
b100110000111011001010100001100100001000011111110110111001011101 %
b100110000111011001010100001100100001000011111110110111001011101 (
1#
#245000
0#
#250000
1!
b1001100001110110010101000011001000010000111111101101110010111010 "
b1001100001110110010101000011001000010000111111101101110010111010 ,
b100100011010001010110 +
b1001100001110110010101000011001000010000111111101101110010111010 %
b1001100001110110010101000011001000010000111111101101110010111010 (
0#
#255000
0!
b110011110001001101010111100110111101111000000010010001101000101 "
b110011110001001101010111100110111101111000000010010001101000101 ,
b10100100011010001010110 +
1#
#260000
1!
b11000011101100101010000110010000100001111111011011100101110101 "
b11000011101100101010000110010000100001111111011011100101110101 ,
b100100011010001010110 +
b11000011101100101010000110010000100001111111011011100101110101 %
b11000011101100101010000110010000100001111111011011100101110101 (
1#
#265000
0#
#270000
0!
b1001111000100110101011110011011110111100000001001000110100010101 "
b1001111000100110101011110011011110111100000001001000110100010101 ,
b10100100011010001010110 +
b110000111011001010100001100100001000011111110110111001011101010 %
b110000111011001010100001100100001000011111110110111001011101010 (
0#
#275000
1!
b110000111011001010100001100100001000011111110110111001011101010 "
b110000111011001010100001100100001000011111110110111001011101010 ,
b100100011010001010110 +
1#
#280000
0!
b11110001001101010111100110111101111000000010010001101000101011 "
b11110001001101010111100110111101111000000010010001101000101011 ,
b10100100011010001010110 +
b1100001110110010101000011001000010000111111101101110010111010100 %
b1100001110110010101000011001000010000111111101101110010111010100 (
1#
#285000
0#
#290000
1!
b1000011101100101010000110010000100001111111011011100101110101001 "
b1000011101100101010000110010000100001111111011011100101110101001 ,
b100100011010001010110 +
b1000011101100101010000110010000100001111111011011100101110101001 %
b1000011101100101010000110010000100001111111011011100101110101001 (
0#
#295000
0!
b111100010011010101111001101111011110000000100100011010001010110 "
b111100010011010101111001101111011110000000100100011010001010110 ,
b10100100011010001010110 +
1#
#300000
1!
b111011001010100001100100001000011111110110111001011101010011 "
b111011001010100001100100001000011111110110111001011101010011 ,
b100100011010001010110 +
b111011001010100001100100001000011111110110111001011101010011 %
b111011001010100001100100001000011111110110111001011101010011 (
1#
#305000
0#
#310000
0!
b1110001001101010111100110111101111000000010010001101000101011001 "
b1110001001101010111100110111101111000000010010001101000101011001 ,
b10100100011010001010110 +
b1110110010101000011001000010000111111101101110010111010100110 %
b1110110010101000011001000010000111111101101110010111010100110 (
0#
#315000
1!
b1110110010101000011001000010000111111101101110010111010100110 "
b1110110010101000011001000010000111111101101110010111010100110 ,
b100100011010001010110 +
1#
#320000
0!
b1100010011010101111001101111011110000000100100011010001010110011 "
b1100010011010101111001101111011110000000100100011010001010110011 ,
b10100100011010001010110 +
b11101100101010000110010000100001111111011011100101110101001100 %
b11101100101010000110010000100001111111011011100101110101001100 (
1#
#325000
0#
#330000
1!
b111011001010100001100100001000011111110110111001011101010011000 "
b111011001010100001100100001000011111110110111001011101010011000 ,
b100100011010001010110 +
b111011001010100001100100001000011111110110111001011101010011000 %
b111011001010100001100100001000011111110110111001011101010011000 (
0#
#335000
0!
b1000100110101011110011011110111100000001001000110100010101100111 "
b1000100110101011110011011110111100000001001000110100010101100111 ,
b10100100011010001010110 +
1#
#340000
1!
b1110110010101000011001000010000111111101101110010111010100110000 "
b1110110010101000011001000010000111111101101110010111010100110000 ,
b100100011010001010110 +
b1110110010101000011001000010000111111101101110010111010100110000 %
b1110110010101000011001000010000111111101101110010111010100110000 (
1#
#345000
0#
#350000
0!
b10011010101111001101111011110000000100100011010001010110011110 "
b10011010101111001101111011110000000100100011010001010110011110 ,
b10100100011010001010110 +
b1101100101010000110010000100001111111011011100101110101001100001 %
b1101100101010000110010000100001111111011011100101110101001100001 (
0#
#355000
1!
b1101100101010000110010000100001111111011011100101110101001100001 "
b1101100101010000110010000100001111111011011100101110101001100001 ,
b100100011010001010110 +
1#
#360000
0!
b100110101011110011011110111100000001001000110100010101100111100 "
b100110101011110011011110111100000001001000110100010101100111100 ,
b10100100011010001010110 +
b1011001010100001100100001000011111110110111001011101010011000011 %
b1011001010100001100100001000011111110110111001011101010011000011 (
1#
#365000
0#
#370000
1!
b110010101000011001000010000111111101101110010111010100110000111 "
b110010101000011001000010000111111101101110010111010100110000111 ,
b100100011010001010110 +
b110010101000011001000010000111111101101110010111010100110000111 %
b110010101000011001000010000111111101101110010111010100110000111 (
0#
#375000
0!
b1001101010111100110111101111000000010010001101000101011001111000 "
b1001101010111100110111101111000000010010001101000101011001111000 ,
b10100100011010001010110 +
1#
#380000
1!
b1100101010000110010000100001111111011011100101110101001100001110 "
b1100101010000110010000100001111111011011100101110101001100001110 ,
b100100011010001010110 +
b1100101010000110010000100001111111011011100101110101001100001110 %
b1100101010000110010000100001111111011011100101110101001100001110 (
1#
#385000
0#
#390000
0!
b110101011110011011110111100000001001000110100010101100111100010 "
b110101011110011011110111100000001001000110100010101100111100010 ,
b10100100011010001010110 +
b1001010100001100100001000011111110110111001011101010011000011101 %
b1001010100001100100001000011111110110111001011101010011000011101 (
0#
#395000
1!
b1001010100001100100001000011111110110111001011101010011000011101 "
b1001010100001100100001000011111110110111001011101010011000011101 ,
b100100011010001010110 +
1#
#400000
0!
b1101010111100110111101111000000010010001101000101011001111000100 "
b1101010111100110111101111000000010010001101000101011001111000100 ,
b10100100011010001010110 +
b10101000011001000010000111111101101110010111010100110000111011 %
b10101000011001000010000111111101101110010111010100110000111011 (
1#
#405000
0#
#410000
1!
b101010000110010000100001111111011011100101110101001100001110110 "
b101010000110010000100001111111011011100101110101001100001110110 ,
b100100011010001010110 +
b101010000110010000100001111111011011100101110101001100001110110 %
b101010000110010000100001111111011011100101110101001100001110110 (
0#
#415000
0!
b1010101111001101111011110000000100100011010001010110011110001001 "
b1010101111001101111011110000000100100011010001010110011110001001 ,
b10100100011010001010110 +
1#
#420000
1!
b1010100001100100001000011111110110111001011101010011000011101100 "
b1010100001100100001000011111110110111001011101010011000011101100 ,
b100100011010001010110 +
b1010100001100100001000011111110110111001011101010011000011101100 %
b1010100001100100001000011111110110111001011101010011000011101100 (
1#
#425000
0#
#430000
0!
b1010111100110111101111000000010010001101000101011001111000100110 "
b1010111100110111101111000000010010001101000101011001111000100110 ,
b10100100011010001010110 +
b101000011001000010000111111101101110010111010100110000111011001 %
b101000011001000010000111111101101110010111010100110000111011001 (
0#
#435000
1!
b101000011001000010000111111101101110010111010100110000111011001 "
b101000011001000010000111111101101110010111010100110000111011001 ,
b100100011010001010110 +
1#
#440000
0!
b101111001101111011110000000100100011010001010110011110001001101 "
b101111001101111011110000000100100011010001010110011110001001101 ,
b10100100011010001010110 +
b1010000110010000100001111111011011100101110101001100001110110010 %
b1010000110010000100001111111011011100101110101001100001110110010 (
1#
#445000
0#
#450000
1!
b100001100100001000011111110110111001011101010011000011101100101 "
b100001100100001000011111110110111001011101010011000011101100101 ,
b100100011010001010110 +
b100001100100001000011111110110111001011101010011000011101100101 %
b100001100100001000011111110110111001011101010011000011101100101 (
0#
#455000
0!
b1011110011011110111100000001001000110100010101100111100010011010 "
b1011110011011110111100000001001000110100010101100111100010011010 ,
b10100100011010001010110 +
1#
#460000
1!
b1000011001000010000111111101101110010111010100110000111011001010 "
b1000011001000010000111111101101110010111010100110000111011001010 ,
b100100011010001010110 +
b1000011001000010000111111101101110010111010100110000111011001010 %
b1000011001000010000111111101101110010111010100110000111011001010 (
1#
#465000
0#
#470000
0!
b1111001101111011110000000100100011010001010110011110001001101010 "
b1111001101111011110000000100100011010001010110011110001001101010 ,
b10100100011010001010110 +
b110010000100001111111011011100101110101001100001110110010101 %
b110010000100001111111011011100101110101001100001110110010101 (
0#
#475000
1!
b110010000100001111111011011100101110101001100001110110010101 "
b110010000100001111111011011100101110101001100001110110010101 ,
b100100011010001010110 +
1#
#480000
0!
b1110011011110111100000001001000110100010101100111100010011010101 "
b1110011011110111100000001001000110100010101100111100010011010101 ,
b10100100011010001010110 +
b1100100001000011111110110111001011101010011000011101100101010 %
b1100100001000011111110110111001011101010011000011101100101010 (
1#
#485000
0#
#490000
1!
b11001000010000111111101101110010111010100110000111011001010100 "
b11001000010000111111101101110010111010100110000111011001010100 ,
b100100011010001010110 +
b11001000010000111111101101110010111010100110000111011001010100 %
b11001000010000111111101101110010111010100110000111011001010100 (
0#
#495000
0!
b1100110111101111000000010010001101000101011001111000100110101011 "
b1100110111101111000000010010001101000101011001111000100110101011 ,
b10100100011010001010110 +
1#
#500000
1!
b110010000100001111111011011100101110101001100001110110010101000 "
b110010000100001111111011011100101110101001100001110110010101000 ,
b100100011010001010110 +
b110010000100001111111011011100101110101001100001110110010101000 %
b110010000100001111111011011100101110101001100001110110010101000 (
1#
#505000
0#
#510000
0!
b11011110111100000001001000110100010101100111100010011010101111 "
b11011110111100000001001000110100010101100111100010011010101111 ,
b10100100011010001010110 +
b1100100001000011111110110111001011101010011000011101100101010000 %
b1100100001000011111110110111001011101010011000011101100101010000 (
0#
#515000
1!
b1100100001000011111110110111001011101010011000011101100101010000 "
b1100100001000011111110110111001011101010011000011101100101010000 ,
b100100011010001010110 +
1#
#520000
0!
b110111101111000000010010001101000101011001111000100110101011110 "
b110111101111000000010010001101000101011001111000100110101011110 ,
b10100100011010001010110 +
b1001000010000111111101101110010111010100110000111011001010100001 %
b1001000010000111111101101110010111010100110000111011001010100001 (
1#
#525000
0#
#530000
1!
b10000100001111111011011100101110101001100001110110010101000011 "
b10000100001111111011011100101110101001100001110110010101000011 ,
b100100011010001010110 +
b10000100001111111011011100101110101001100001110110010101000011 %
b10000100001111111011011100101110101001100001110110010101000011 (
0#
#535000
0!
b1101111011110000000100100011010001010110011110001001101010111100 "
b1101111011110000000100100011010001010110011110001001101010111100 ,
b10100100011010001010110 +
1#
#540000
1!
b100001000011111110110111001011101010011000011101100101010000110 "
b100001000011111110110111001011101010011000011101100101010000110 ,
b100100011010001010110 +
b100001000011111110110111001011101010011000011101100101010000110 %
b100001000011111110110111001011101010011000011101100101010000110 (
1#
#545000
0#
#550000
0!
b111101111000000010010001101000101011001111000100110101011110011 "
b111101111000000010010001101000101011001111000100110101011110011 ,
b10100100011010001010110 +
b1000010000111111101101110010111010100110000111011001010100001100 %
b1000010000111111101101110010111010100110000111011001010100001100 (
0#
#555000
1!
b1000010000111111101101110010111010100110000111011001010100001100 "
b1000010000111111101101110010111010100110000111011001010100001100 ,
b100100011010001010110 +
1#
#560000
0!
b1111011110000000100100011010001010110011110001001101010111100110 "
b1111011110000000100100011010001010110011110001001101010111100110 ,
b10100100011010001010110 +
b100001111111011011100101110101001100001110110010101000011001 %
b100001111111011011100101110101001100001110110010101000011001 (
1#
#565000
0#
#570000
1!
b1000011111110110111001011101010011000011101100101010000110010 "
b1000011111110110111001011101010011000011101100101010000110010 ,
b100100011010001010110 +
b1000011111110110111001011101010011000011101100101010000110010 %
b1000011111110110111001011101010011000011101100101010000110010 (
0#
#575000
0!
b1110111100000001001000110100010101100111100010011010101111001101 "
b1110111100000001001000110100010101100111100010011010101111001101 ,
b10100100011010001010110 +
1#
#580000
1!
b10000111111101101110010111010100110000111011001010100001100100 "
b10000111111101101110010111010100110000111011001010100001100100 ,
b100100011010001010110 +
b10000111111101101110010111010100110000111011001010100001100100 %
b10000111111101101110010111010100110000111011001010100001100100 (
1#
#585000
0#
#590000
0!
b1011110000000100100011010001010110011110001001101010111100110111 "
b1011110000000100100011010001010110011110001001101010111100110111 ,
b10100100011010001010110 +
b100001111111011011100101110101001100001110110010101000011001000 %
b100001111111011011100101110101001100001110110010101000011001000 (
0#
#595000
1!
b100001111111011011100101110101001100001110110010101000011001000 "
b100001111111011011100101110101001100001110110010101000011001000 ,
b100100011010001010110 +
1#
#600000
0!
b111100000001001000110100010101100111100010011010101111001101111 "
b111100000001001000110100010101100111100010011010101111001101111 ,
b10100100011010001010110 +
b1000011111110110111001011101010011000011101100101010000110010000 %
b1000011111110110111001011101010011000011101100101010000110010000 (
1#
#605000
0#
#610000
1!
b111111101101110010111010100110000111011001010100001100100001 "
b111111101101110010111010100110000111011001010100001100100001 ,
b100100011010001010110 +
b111111101101110010111010100110000111011001010100001100100001 %
b111111101101110010111010100110000111011001010100001100100001 (
0#
#615000
0!
b1111000000010010001101000101011001111000100110101011110011011110 "
b1111000000010010001101000101011001111000100110101011110011011110 ,
b10100100011010001010110 +
1#
#620000
1!
b1111111011011100101110101001100001110110010101000011001000010 "
b1111111011011100101110101001100001110110010101000011001000010 ,
b100100011010001010110 +
b1111111011011100101110101001100001110110010101000011001000010 %
b1111111011011100101110101001100001110110010101000011001000010 (
1#
#625000
0#
#630000
0!
b1100000001001000110100010101100111100010011010101111001101111011 "
b1100000001001000110100010101100111100010011010101111001101111011 ,
b10100100011010001010110 +
b11111110110111001011101010011000011101100101010000110010000100 %
b11111110110111001011101010011000011101100101010000110010000100 (
0#
#635000
1!
b11111110110111001011101010011000011101100101010000110010000100 "
b11111110110111001011101010011000011101100101010000110010000100 ,
b100100011010001010110 +
1#
#640000
0!
b1000000010010001101000101011001111000100110101011110011011110111 "
b1000000010010001101000101011001111000100110101011110011011110111 ,
b10100100011010001010110 +
b111111101101110010111010100110000111011001010100001100100001000 %
b111111101101110010111010100110000111011001010100001100100001000 (
1#
#645000
0#
#650000
1!
b1111111011011100101110101001100001110110010101000011001000010000 "
b1111111011011100101110101001100001110110010101000011001000010000 ,
b100100011010001010110 +
b1111111011011100101110101001100001110110010101000011001000010000 %
b1111111011011100101110101001100001110110010101000011001000010000 (
0#
#655000
0!
b100100011010001010110011110001001101010111100110111101111 "
b100100011010001010110011110001001101010111100110111101111 ,
b10100100011010001010110 +
1#
#660000
1!
b1111110110111001011101010011000011101100101010000110010000100001 "
b1111110110111001011101010011000011101100101010000110010000100001 ,
b100100011010001010110 +
b1111110110111001011101010011000011101100101010000110010000100001 %
b1111110110111001011101010011000011101100101010000110010000100001 (
1#
#665000
0#
#670000
0!
b10010001101000101011001111000100110101011110011011110111100 "
b10010001101000101011001111000100110101011110011011110111100 ,
b10100100011010001010110 +
b1111101101110010111010100110000111011001010100001100100001000011 %
b1111101101110010111010100110000111011001010100001100100001000011 (
0#
#675000
1!
b1111101101110010111010100110000111011001010100001100100001000011 "
b1111101101110010111010100110000111011001010100001100100001000011 ,
b100100011010001010110 +
1#
#680000
0!
b100100011010001010110011110001001101010111100110111101111000 "
b100100011010001010110011110001001101010111100110111101111000 ,
b10100100011010001010110 +
b1111011011100101110101001100001110110010101000011001000010000111 %
b1111011011100101110101001100001110110010101000011001000010000111 (
1#
#685000
0#
#690000
1!
b1110110111001011101010011000011101100101010000110010000100001111 "
b1110110111001011101010011000011101100101010000110010000100001111 ,
b100100011010001010110 +
b1110110111001011101010011000011101100101010000110010000100001111 %
b1110110111001011101010011000011101100101010000110010000100001111 (
0#
#695000
0!
b1001000110100010101100111100010011010101111001101111011110000 "
b1001000110100010101100111100010011010101111001101111011110000 ,
b10100100011010001010110 +
1#
#700000
1!
b1101101110010111010100110000111011001010100001100100001000011111 "
b1101101110010111010100110000111011001010100001100100001000011111 ,
b100100011010001010110 +
b1101101110010111010100110000111011001010100001100100001000011111 %
b1101101110010111010100110000111011001010100001100100001000011111 (
1#
#705000
0#
#710000
0!
b100100011010001010110011110001001101010111100110111101111000000 "
b100100011010001010110011110001001101010111100110111101111000000 ,
b10100100011010001010110 +
b1011011100101110101001100001110110010101000011001000010000111111 %
b1011011100101110101001100001110110010101000011001000010000111111 (
0#
#715000
1!
b1011011100101110101001100001110110010101000011001000010000111111 "
b1011011100101110101001100001110110010101000011001000010000111111 ,
b100100011010001010110 +
1#
#720000
0!
b1001000110100010101100111100010011010101111001101111011110000000 "
b1001000110100010101100111100010011010101111001101111011110000000 ,
b10100100011010001010110 +
b110111001011101010011000011101100101010000110010000100001111111 %
b110111001011101010011000011101100101010000110010000100001111111 (
1#
#725000
0#
#730000
1!
b1101110010111010100110000111011001010100001100100001000011111110 "
b1101110010111010100110000111011001010100001100100001000011111110 ,
b100100011010001010110 +
b1101110010111010100110000111011001010100001100100001000011111110 %
b1101110010111010100110000111011001010100001100100001000011111110 (
0#
#735000
0!
b10001101000101011001111000100110101011110011011110111100000001 "
b10001101000101011001111000100110101011110011011110111100000001 ,
b10100100011010001010110 +
1#
#740000
1!
b1011100101110101001100001110110010101000011001000010000111111101 "
b1011100101110101001100001110110010101000011001000010000111111101 ,
b100100011010001010110 +
b1011100101110101001100001110110010101000011001000010000111111101 %
b1011100101110101001100001110110010101000011001000010000111111101 (
1#
#745000
0#
#750000
0!
b1000110100010101100111100010011010101111001101111011110000000100 "
b1000110100010101100111100010011010101111001101111011110000000100 ,
b10100100011010001010110 +
b111001011101010011000011101100101010000110010000100001111111011 %
b111001011101010011000011101100101010000110010000100001111111011 (
0#
#755000
1!
b111001011101010011000011101100101010000110010000100001111111011 "
b111001011101010011000011101100101010000110010000100001111111011 ,
b100100011010001010110 +
1#
#760000
0!
b1101000101011001111000100110101011110011011110111100000001001 "
b1101000101011001111000100110101011110011011110111100000001001 ,
b10100100011010001010110 +
b1110010111010100110000111011001010100001100100001000011111110110 %
b1110010111010100110000111011001010100001100100001000011111110110 (
1#
#765000
0#
#770000
1!
b1100101110101001100001110110010101000011001000010000111111101101 "
b1100101110101001100001110110010101000011001000010000111111101101 ,
b100100011010001010110 +
b1100101110101001100001110110010101000011001000010000111111101101 %
b1100101110101001100001110110010101000011001000010000111111101101 (
0#
#775000
0!
b11010001010110011110001001101010111100110111101111000000010010 "
b11010001010110011110001001101010111100110111101111000000010010 ,
b10100100011010001010110 +
1#
#780000
1!
b1001011101010011000011101100101010000110010000100001111111011011 "
b1001011101010011000011101100101010000110010000100001111111011011 ,
b100100011010001010110 +
b1001011101010011000011101100101010000110010000100001111111011011 %
b1001011101010011000011101100101010000110010000100001111111011011 (
1#
#785000
0#
#790000
0!
b1101000101011001111000100110101011110011011110111100000001001000 "
b1101000101011001111000100110101011110011011110111100000001001000 ,
b10100100011010001010110 +
b10111010100110000111011001010100001100100001000011111110110111 %
b10111010100110000111011001010100001100100001000011111110110111 (
0#
#795000
1!
b10111010100110000111011001010100001100100001000011111110110111 "
b10111010100110000111011001010100001100100001000011111110110111 ,
b100100011010001010110 +
1#
#800000
0!
b1010001010110011110001001101010111100110111101111000000010010001 "
b1010001010110011110001001101010111100110111101111000000010010001 ,
b10100100011010001010110 +
b101110101001100001110110010101000011001000010000111111101101110 %
b101110101001100001110110010101000011001000010000111111101101110 (
1#
#805000
0#
#810000
1!
b1011101010011000011101100101010000110010000100001111111011011100 "
b1011101010011000011101100101010000110010000100001111111011011100 ,
b100100011010001010110 +
b1011101010011000011101100101010000110010000100001111111011011100 %
b1011101010011000011101100101010000110010000100001111111011011100 (
0#
#815000
0!
b100010101100111100010011010101111001101111011110000000100100011 "
b100010101100111100010011010101111001101111011110000000100100011 ,
b10100100011010001010110 +
1#
#820000
1!
b111010100110000111011001010100001100100001000011111110110111001 "
b111010100110000111011001010100001100100001000011111110110111001 ,
b100100011010001010110 +
b111010100110000111011001010100001100100001000011111110110111001 %
b111010100110000111011001010100001100100001000011111110110111001 (
1#
#825000
0#
